README.rst
setup.cfg
setup.py
arst/__init__.py
arst/command_diff.py
arst/command_edit.py
arst/command_help.py
arst/command_lls.py
arst/command_ls.py
arst/command_push.py
arst/command_pwd.py
arst/command_tree.py
arst/file_resolver.py
arst/mainapp.py
arst/program_arguments.py
arst/project_reader.py
arst/py.typed
arst.egg-info/PKG-INFO
arst.egg-info/SOURCES.txt
arst.egg-info/dependency_links.txt
arst.egg-info/entry_points.txt
arst.egg-info/requires.txt
arst.egg-info/top_level.txt