Metadata-Version: 1.0
Name: arst
Version: 1.3.0
Summary: Poor man's yo generator.
Home-page: UNKNOWN
Author: Bogdan Mustiata
Author-email: bogdan.mustiata@gmail.com
License: BSD
Platform: UNKNOWN
